minlog/__init__.py
minlog/core.py
minlog/panorama.py
minlog/utils.py
minlog/viewer_template.py
minlog_py-0.2.1.dist-info/METADATA
minlog_py-0.2.1.dist-info/WHEEL
minlog_py-0.2.1.dist-info/top_level.txt
minlog_py-0.2.1.dist-info/RECORD
