Metadata-Version: 2.4
Name: minlog-py
Version: 0.2.1
Summary: A concise, production-ready Python logging toolkit.
Author-email: Min <yuzhmin@126.com>
Project-URL: Homepage, https://github.com/MinBeing/MinLog
Classifier: Programming Language :: Python :: 3
Classifier: License :: OSI Approved :: MIT License
Classifier: Operating System :: OS Independent
Requires-Python: >=3.7
